NOMTrainer/NOMTrainer.py
NOMTrainer/__init__.py
NOMTrainer-1.1.8.dist-info/METADATA
NOMTrainer-1.1.8.dist-info/WHEEL
NOMTrainer-1.1.8.dist-info/top_level.txt
NOMTrainer-1.1.8.dist-info/RECORD
