Metadata-Version: 2.1
Name: NOMTrainer
Version: 1.1.8
Summary: A Trainer for Neural Object Model (NOM) in Tensorflow.
Home-page: https://github.com/LadderCSSA/NOMTrainer
Author: CSSA
Author-email: ladder.cssa@gmail.com
Classifier: Programming Language :: Python :: 3
Classifier: License :: OSI Approved :: MIT License
Classifier: Operating System :: OS Independent
Requires-Python: >=3.9
